jupyter_ai_agents/__init__.py
jupyter_ai_agents/__version__.py
jupyter_ai_agents/models.py
jupyter_ai_agents/serverapplication.py
jupyter_ai_agents/utils.py
jupyter_ai_agents/agents/__init__.py
jupyter_ai_agents/agents/base.py
jupyter_ai_agents/agents/explain_error.py
jupyter_ai_agents/agents/prompt.py
jupyter_ai_agents/agents/utils.py
jupyter_ai_agents/cli/__init__.py
jupyter_ai_agents/cli/app.py
jupyter_ai_agents/cli/base.py
jupyter_ai_agents/cli/consoleapp.py
jupyter_ai_agents/handlers/__init__.py
jupyter_ai_agents/handlers/base.py
jupyter_ai_agents/handlers/agents/__init__.py
jupyter_ai_agents/handlers/agents/handler.py
jupyter_ai_agents/handlers/agents/manager.py
jupyter_ai_agents/handlers/config/__init__.py
jupyter_ai_agents/handlers/config/handler.py
jupyter_ai_agents/handlers/index/__init__.py
jupyter_ai_agents/handlers/index/handler.py
jupyter_ai_agents/providers/__init__.py
jupyter_ai_agents/providers/anthropic.py
jupyter_ai_agents/providers/azure_openai.py
jupyter_ai_agents/providers/bedrock.py
jupyter_ai_agents/providers/github_copilot.py
jupyter_ai_agents/providers/openai.py
jupyter_ai_agents/server/__init__.py
jupyter_ai_agents/server/agents.py
jupyter_ai_agents/server/main.py
jupyter_ai_agents/server/api/__init__.py
jupyter_ai_agents/static/README.md
jupyter_ai_agents/templates/index.html
jupyter_ai_agents/tests/__init__.py
jupyter_ai_agents/tests/test_integration_anthropic.py
jupyter_ai_agents/tools/__init__.py
jupyter_ai_agents/tools/tools.py
jupyter_ai_agents-0.12.0.data/data/etc/jupyter/jupyter_notebook_config.d/jupyter_ai_agents.json
jupyter_ai_agents-0.12.0.data/data/etc/jupyter/jupyter_server_config.d/jupyter_ai_agents.json
jupyter_ai_agents-0.12.0.dist-info/METADATA
jupyter_ai_agents-0.12.0.dist-info/WHEEL
jupyter_ai_agents-0.12.0.dist-info/entry_points.txt
jupyter_ai_agents-0.12.0.dist-info/licenses/LICENSE
jupyter_ai_agents-0.12.0.dist-info/RECORD
