Metadata-Version: 2.4
Name: jupyter_ai_agents
Version: 0.12.0
Project-URL: Home, https://github.com/datalayer/jupyter-ai-agents
Author-email: Datalayer <info@datalayer.io>
License: BSD 3-Clause License
License-File: LICENSE
Keywords: Jupyter
Classifier: Framework :: Jupyter
Classifier: Intended Audience :: Developers
Classifier: Intended Audience :: Science/Research
Classifier: Intended Audience :: System Administrators
Classifier: License :: OSI Approved :: BSD License
Classifier: Programming Language :: Python
Classifier: Programming Language :: Python :: 3
Classifier: Programming Language :: Python :: 3.9
Classifier: Programming Language :: Python :: 3.10
Classifier: Programming Language :: Python :: 3.11
Requires-Python: >=3.9
Requires-Dist: anyio
Requires-Dist: datalayer-core
Requires-Dist: fastapi
Requires-Dist: jupyter-kernel-client
Requires-Dist: jupyter-nbmodel-client
Requires-Dist: jupyter-server<3,>=2.10
Requires-Dist: langchain
Requires-Dist: langchain-anthropic
Requires-Dist: langchain-aws
Requires-Dist: langchain-github-copilot
Requires-Dist: langchain-openai
Requires-Dist: pydantic-settings
Requires-Dist: python-dotenv
Requires-Dist: uvicorn
Provides-Extra: example
Requires-Dist: jupyter-server-ydoc; extra == 'example'
Provides-Extra: lint
Requires-Dist: mdformat-gfm>=0.3.5; extra == 'lint'
Requires-Dist: mdformat>0.7; extra == 'lint'
Requires-Dist: ruff; extra == 'lint'
Provides-Extra: test
Requires-Dist: ipykernel; extra == 'test'
Requires-Dist: pytest>=7.0; extra == 'test'
Provides-Extra: typing
Requires-Dist: mypy>=0.990; extra == 'typing'
